LICENSE
MANIFEST.in
README.md
setup.cfg
setup.py
django_vacancies.egg-info/PKG-INFO
django_vacancies.egg-info/SOURCES.txt
django_vacancies.egg-info/dependency_links.txt
django_vacancies.egg-info/top_level.txt
docs/.gitkeep
vacancies/__init__.py
vacancies/admin.py
vacancies/apps.py
vacancies/storage.py
vacancies/urls.py
vacancies/utils.py
vacancies/views.py
vacancies/locale/de/LC_MESSAGES/django.po
vacancies/migrations/0001_initial.py
vacancies/migrations/__init__.py
vacancies/models/__init__.py
vacancies/models/contact_person.py
vacancies/models/location.py
vacancies/models/vacancy.py
vacancies/static/vacancies/css/admin.css
vacancies/templates/vacancies/vacancies_base.html
vacancies/templates/vacancies/vacancy_detail.html
vacancies/templates/vacancies/vacancy_list.html